prompt_versioner/__init__.py
prompt_versioner/app/__init__.py
prompt_versioner/app/config.py
prompt_versioner/app/controllers/__init__.py
prompt_versioner/app/controllers/alerts_view.py
prompt_versioner/app/controllers/export_import_view.py
prompt_versioner/app/controllers/prompts_view.py
prompt_versioner/app/controllers/versions_view.py
prompt_versioner/app/flask_builder.py
prompt_versioner/app/models/__init__.py
prompt_versioner/app/models/alert_models.py
prompt_versioner/app/models/diff_models.py
prompt_versioner/app/services/__init__.py
prompt_versioner/app/services/alert_service/__init__.py
prompt_versioner/app/services/alert_service/alert_service.py
prompt_versioner/app/services/alert_service/monitoring.py
prompt_versioner/app/services/diff_service/__init__.py
prompt_versioner/app/services/diff_service/diff_engine.py
prompt_versioner/app/services/diff_service/diff_service.py
prompt_versioner/app/services/metrics_service/__init__.py
prompt_versioner/app/services/metrics_service/metrics_service.py
prompt_versioner/cli/__init__.py
prompt_versioner/cli/commands/__init__.py
prompt_versioner/cli/commands/dashboard.py
prompt_versioner/cli/commands/diff.py
prompt_versioner/cli/commands/init.py
prompt_versioner/cli/commands/management.py
prompt_versioner/cli/commands/pricing.py
prompt_versioner/cli/commands/prompts.py
prompt_versioner/cli/main_cli.py
prompt_versioner/cli/utils/__init__.py
prompt_versioner/cli/utils/formatters.py
prompt_versioner/core/__init__.py
prompt_versioner/core/enums.py
prompt_versioner/core/test_context.py
prompt_versioner/core/version_manager.py
prompt_versioner/core/versioner.py
prompt_versioner/metrics/__init__.py
prompt_versioner/metrics/aggregator.py
prompt_versioner/metrics/analyzer.py
prompt_versioner/metrics/calculator.py
prompt_versioner/metrics/models.py
prompt_versioner/metrics/pricing.py
prompt_versioner/metrics/tracker.py
prompt_versioner/storage/__init__.py
prompt_versioner/storage/annotations.py
prompt_versioner-0.3.1.dist-info/LICENSE
prompt_versioner-0.3.1.dist-info/METADATA
prompt_versioner-0.3.1.dist-info/WHEEL
prompt_versioner-0.3.1.dist-info/entry_points.txt
prompt_versioner-0.3.1.dist-info/RECORD
