Metadata-Version: 2.1
Name: prompt-versioner
Version: 0.3.1
Summary: Intelligent versioning system for LLM prompts with Git integration
Home-page: https://github.com/pepes97/prompt-versioner
License: MIT
Author: Sveva Pepe
Author-email: sveva.pepe@gmail.com
Requires-Python: >=3.11
Classifier: License :: OSI Approved :: MIT License
Classifier: Programming Language :: Python :: 3
Classifier: Programming Language :: Python :: 3.11
Classifier: Programming Language :: Python :: 3.12
Requires-Dist: click (>=8.1.7)
Requires-Dist: flask (>=3.0.0)
Requires-Dist: pyyaml (>=6.0.3)
Requires-Dist: rich (>=13.7.0)
Project-URL: Documentation, https://pepes97.github.io/prompt-versioner/
Project-URL: Repository, https://github.com/pepes97/prompt-versioner
